eth_address_generator/__init__.py
eth_address_generator/generator.py
eth_address_generator-0.1.0.dist-info/LICENSE
eth_address_generator-0.1.0.dist-info/METADATA
eth_address_generator-0.1.0.dist-info/WHEEL
eth_address_generator-0.1.0.dist-info/top_level.txt
eth_address_generator-0.1.0.dist-info/RECORD
